uncompyle6/__init__.py
uncompyle6/code_fns.py
uncompyle6/linenumbers.py
uncompyle6/main.py
uncompyle6/parser.py
uncompyle6/scanner.py
uncompyle6/show.py
uncompyle6/util.py
uncompyle6/verify.py
uncompyle6/version.py
uncompyle6/bin/__init__.py
uncompyle6/bin/pydisassemble.py
uncompyle6/bin/uncompile.py
uncompyle6/parsers/__init__.py
uncompyle6/parsers/parse10.py
uncompyle6/parsers/parse11.py
uncompyle6/parsers/parse12.py
uncompyle6/parsers/parse13.py
uncompyle6/parsers/parse14.py
uncompyle6/parsers/parse15.py
uncompyle6/parsers/parse16.py
uncompyle6/parsers/parse2.py
uncompyle6/parsers/parse21.py
uncompyle6/parsers/parse22.py
uncompyle6/parsers/parse23.py
uncompyle6/parsers/parse24.py
uncompyle6/parsers/parse25.py
uncompyle6/parsers/parse26.py
uncompyle6/parsers/parse27.py
uncompyle6/parsers/parse3.py
uncompyle6/parsers/parse30.py
uncompyle6/parsers/parse31.py
uncompyle6/parsers/parse32.py
uncompyle6/parsers/parse33.py
uncompyle6/parsers/parse34.py
uncompyle6/parsers/parse35.py
uncompyle6/parsers/parse36.py
uncompyle6/parsers/parse37.py
uncompyle6/parsers/parse37base.py
uncompyle6/parsers/parse38.py
uncompyle6/parsers/treenode.py
uncompyle6/parsers/reducecheck/__init__.py
uncompyle6/parsers/reducecheck/and_check.py
uncompyle6/parsers/reducecheck/and_not_check.py
uncompyle6/parsers/reducecheck/aug_assign.py
uncompyle6/parsers/reducecheck/except_handler.py
uncompyle6/parsers/reducecheck/except_handler_else.py
uncompyle6/parsers/reducecheck/for_block_check.py
uncompyle6/parsers/reducecheck/ifelsestmt.py
uncompyle6/parsers/reducecheck/ifelsestmt2.py
uncompyle6/parsers/reducecheck/iflaststmt.py
uncompyle6/parsers/reducecheck/ifstmt.py
uncompyle6/parsers/reducecheck/ifstmt2.py
uncompyle6/parsers/reducecheck/ifstmts_jump.py
uncompyle6/parsers/reducecheck/joined_str_check.py
uncompyle6/parsers/reducecheck/or_check.py
uncompyle6/parsers/reducecheck/pop_return.py
uncompyle6/parsers/reducecheck/testtrue.py
uncompyle6/parsers/reducecheck/tryelsestmt.py
uncompyle6-3.9.3.dist-info/COPYING
uncompyle6-3.9.3.dist-info/METADATA
uncompyle6-3.9.3.dist-info/WHEEL
uncompyle6-3.9.3.dist-info/entry_points.txt
uncompyle6-3.9.3.dist-info/top_level.txt
uncompyle6-3.9.3.dist-info/zip-safe
uncompyle6-3.9.3.dist-info/RECORD
